gemini_key_rotater/__init__.py
gemini_key_rotater/manager.py
gemini_key_rotater-1.0.0.dist-info/METADATA
gemini_key_rotater-1.0.0.dist-info/WHEEL
gemini_key_rotater-1.0.0.dist-info/top_level.txt
gemini_key_rotater-1.0.0.dist-info/RECORD
