Metadata-Version: 2.1
Name: gemini-key-rotater
Version: 1.0.0
Summary: A package to rotate Gemini API keys based on rate limits.
Home-page: https://github.com/santoshkanumuri/gemini-key-rotater
Author: Santosh Kanumuri
Author-email: pavan.kanumuri@hotmail.com
Classifier: Development Status :: 3 - Alpha
Classifier: Intended Audience :: Developers
Classifier: Programming Language :: Python :: 3
Classifier: License :: OSI Approved :: MIT License
Classifier: Operating System :: OS Independent
Requires-Python: >=3.6
